purrfectmeow/__init__.py
purrfectmeow/meow/chaus.py
purrfectmeow/meow/felis.py
purrfectmeow/meow/kitty.py
purrfectmeow/tc01_spl/__init__.py
purrfectmeow/tc01_spl/base.py
purrfectmeow/tc01_spl/markdown.py
purrfectmeow/tc01_spl/ocr.py
purrfectmeow/tc01_spl/simple.py
purrfectmeow/tc02_mlt/__init__.py
purrfectmeow/tc02_mlt/base.py
purrfectmeow/tc02_mlt/separate.py
purrfectmeow/tc02_mlt/token.py
purrfectmeow/tc03_wcm/__init__.py
purrfectmeow/tc03_wcm/base.py
purrfectmeow/tc03_wcm/local.py
purrfectmeow/tc04_kmn/__init__.py
purrfectmeow/tc04_kmn/base.py
purrfectmeow/tc04_kmn/cosine.py
purrfectmeow/tc05_knj/__init__.py
purrfectmeow/tc05_knj/base.py
purrfectkit-0.2.6.dist-info/licenses/LICENSE
purrfectkit-0.2.6.dist-info/WHEEL
purrfectkit-0.2.6.dist-info/METADATA
purrfectkit-0.2.6.dist-info/RECORD
